{
  "product_generation_request_id": "EON_ID123456789",
  "json_version": "1.0",
  "request_type": "create",
  "request_date": "2022-09-09",
  "environment": "FT",
  "sku": "TESTSK675",
  "ams_sku": "TESTSKU222",
  "client_id": "1002",
  "productname": "TESPRODUCT123",
  "material": "TESPRODUCT",
  "brand": "TESPRODUCT",
  "prices": {
    "ek": "",
    "monthly_uplift_gross": "",
    "monthly_uplift_net": "",
    "monthly_uplift_gross_on_cancellation": "",
    "monthly_uplift_net_on_cancellation": "",
    "additional_payment_value_gross": "",
    "additional_payment_value_net": "",
    "uvp": "",
    "retail_price_gross": "",
    "repayment_per_year": "",
    "seperate_billing_on_monthly_repayed": "",
    "vat_rate": "",
    "billing_period": ""
  },  
  "qty_unit": "ST",
  "measurement_unit": "cm",
  "length": "20.5",
  "width": "10.5",
  "height": "2.5",
  "weight": "5",
  "weight_unit": "kg",  
  "handover_type": "",
  "returnable": "",
  "serial_number": 1,
  "phone_number": 1,
  "is_reward": 1,
  "reward_type": "ova_reward",
  "bonus_coop": "",
  "plb": "",
  "main_argument_1": "",
  "main_argument_2": "",
  "main_argument_3": "",
  "legal_copy": "",
  "foot_note": "",
  "nkb": 1,
  "special_bonus": 1,
  "start_date": "YYYY-MM-DD hh:mm",
  "end_date": "YYYY-MM-DD hh:mm"
}
